hertz/__init__.py
hertz-1.2.0.dist-info/LICENSE
hertz-1.2.0.dist-info/METADATA
hertz-1.2.0.dist-info/WHEEL
hertz-1.2.0.dist-info/top_level.txt
hertz-1.2.0.dist-info/RECORD
